core_utils/__init__.py
core_utils/data_utils.py
core_utils/decorators.py
core_utils/enum_utils.py
core_utils/env_utils.py
core_utils/file_utils.py
core_utils/formatting_utils.py
core_utils/hash_utils.py
core_utils/print_comments.py
core_utils/py.typed
core_utils/pydantic_utils.py
core_utils/python_utils.py
core_utils/requirements_utils.py
core_utils/toml_utils.py
core_utils/url_utils.py
core_utils/validators.py
turintech_utils-2.0.1.dist-info/METADATA
turintech_utils-2.0.1.dist-info/WHEEL
turintech_utils-2.0.1.dist-info/licenses/LICENSE
turintech_utils-2.0.1.dist-info/RECORD
